proabc_2/MarkovModels/HEAVY.hmm
proabc_2/MarkovModels/HEAVY.hmm.h3f
proabc_2/MarkovModels/HEAVY.hmm.h3i
proabc_2/MarkovModels/HEAVY.hmm.h3m
proabc_2/MarkovModels/HEAVY.hmm.h3p
proabc_2/MarkovModels/KAPPA.hmm
proabc_2/MarkovModels/KAPPA.hmm.h3f
proabc_2/MarkovModels/KAPPA.hmm.h3i
proabc_2/MarkovModels/KAPPA.hmm.h3m
proabc_2/MarkovModels/KAPPA.hmm.h3p
proabc_2/MarkovModels/LAMBDA.hmm
proabc_2/MarkovModels/LAMBDA.hmm.h3f
proabc_2/MarkovModels/LAMBDA.hmm.h3i
proabc_2/MarkovModels/LAMBDA.hmm.h3m
proabc_2/MarkovModels/LAMBDA.hmm.h3p
proabc_2/ParseHmmer.py
proabc_2/__init__.py
proabc_2/clr_fun.py
proabc_2/cnn.py
proabc_2/data/Sparse_encoding_v2.txt
proabc_2/data/proABC_v2.data-00000-of-00002
proabc_2/data/proABC_v2.data-00001-of-00002
proabc_2/data/proABC_v2.index
proabc_2/database/IGHDp.fasta
proabc_2/database/IGHDp.fasta.phr
proabc_2/database/IGHDp.fasta.pin
proabc_2/database/IGHDp.fasta.pog
proabc_2/database/IGHDp.fasta.psd
proabc_2/database/IGHDp.fasta.psi
proabc_2/database/IGHDp.fasta.psq
proabc_2/database/IGHJp.fasta
proabc_2/database/IGHJp.fasta.phr
proabc_2/database/IGHJp.fasta.pin
proabc_2/database/IGHJp.fasta.pog
proabc_2/database/IGHJp.fasta.psd
proabc_2/database/IGHJp.fasta.psi
proabc_2/database/IGHJp.fasta.psq
proabc_2/database/IGHVp.fasta
proabc_2/database/IGHVp.fasta.phr
proabc_2/database/IGHVp.fasta.pin
proabc_2/database/IGHVp.fasta.pog
proabc_2/database/IGHVp.fasta.psd
proabc_2/database/IGHVp.fasta.psi
proabc_2/database/IGHVp.fasta.psq
proabc_2/database/IGKJp.fasta
proabc_2/database/IGKJp.fasta.phr
proabc_2/database/IGKJp.fasta.pin
proabc_2/database/IGKJp.fasta.pog
proabc_2/database/IGKJp.fasta.psd
proabc_2/database/IGKJp.fasta.psi
proabc_2/database/IGKJp.fasta.psq
proabc_2/database/IGKVp.fasta
proabc_2/database/IGKVp.fasta.phr
proabc_2/database/IGKVp.fasta.pin
proabc_2/database/IGKVp.fasta.pog
proabc_2/database/IGKVp.fasta.psd
proabc_2/database/IGKVp.fasta.psi
proabc_2/database/IGKVp.fasta.psq
proabc_2/database/IGLJp.fasta
proabc_2-0.1.2.dist-info/LICENSE
proabc_2-0.1.2.dist-info/METADATA
proabc_2-0.1.2.dist-info/WHEEL
proabc_2-0.1.2.dist-info/entry_points.txt
proabc_2-0.1.2.dist-info/RECORD
