Metadata-Version: 2.1
Name: proabc-2
Version: 0.1.2
Summary: Predicts the antibody residues that will make contact with the antigen and the type of interaction using a Convolutional Neural Network.
License: Apache-2.0
Author: BonvinLab
Author-email: bonvinlab.support@uu.nl
Requires-Python: ==3.7.*
Classifier: Development Status :: 5 - Production/Stable
Classifier: Intended Audience :: Science/Research
Classifier: License :: OSI Approved :: Apache Software License
Classifier: Operating System :: Unix
Classifier: Programming Language :: Python :: 3
Classifier: Programming Language :: Python :: 3.7
Classifier: Topic :: Scientific/Engineering :: Bio-Informatics
Requires-Dist: biopython (==1.74)
Requires-Dist: numpy (>=1.17,<2.0)
Requires-Dist: pandas (>=0.25,<0.26)
Requires-Dist: protobuf (<=3.20.1)
Requires-Dist: tensorflow (==1.14.0)
